py_jaxtyping/__init__.py
py_jaxtyping/main.py
py_jaxtyping/schemas.py
py_jaxtyping-0.1.5.dist-info/METADATA
py_jaxtyping-0.1.5.dist-info/WHEEL
py_jaxtyping-0.1.5.dist-info/top_level.txt
py_jaxtyping-0.1.5.dist-info/RECORD
