Metadata-Version: 2.1
Name: py-jaxtyping
Version: 0.1.5
Summary: Pydantic support for Jaxtyping array annotations
Author-email: Marcel Claramunt <marcel@moveread.com>
Project-URL: repo, https://github.com/moveread/REPO.git
Requires-Python: >=3.10
Requires-Dist: pydantic
Requires-Dist: numpy
